fakturace/__init__.py
fakturace/cli.py
fakturace/data.py
fakturace/invoices.py
fakturace/py.typed
fakturace/rates.py
fakturace/storage.py
fakturace/test_storage.py
fakturace-0.7.2.dist-info/LICENSE
fakturace-0.7.2.dist-info/METADATA
fakturace-0.7.2.dist-info/WHEEL
fakturace-0.7.2.dist-info/entry_points.txt
fakturace-0.7.2.dist-info/top_level.txt
fakturace-0.7.2.dist-info/RECORD
